chuk_mcp_solver/__init__.py
chuk_mcp_solver/cache.py
chuk_mcp_solver/config.py
chuk_mcp_solver/diagnostics.py
chuk_mcp_solver/models.py
chuk_mcp_solver/observability.py
chuk_mcp_solver/server.py
chuk_mcp_solver/validation.py
chuk_mcp_solver/providers/__init__.py
chuk_mcp_solver/solver/__init__.py
chuk_mcp_solver/solver/provider.py
chuk_mcp_solver/solver/ortools/__init__.py
chuk_mcp_solver/solver/ortools/allocation.py
chuk_mcp_solver/solver/ortools/assignment.py
chuk_mcp_solver/solver/ortools/constraints.py
chuk_mcp_solver/solver/ortools/objectives.py
chuk_mcp_solver/solver/ortools/responses.py
chuk_mcp_solver/solver/ortools/routing.py
chuk_mcp_solver/solver/ortools/scheduling.py
chuk_mcp_solver/solver/ortools/solver.py
chuk_mcp_solver-0.3.4.dist-info/METADATA
chuk_mcp_solver-0.3.4.dist-info/WHEEL
chuk_mcp_solver-0.3.4.dist-info/entry_points.txt
chuk_mcp_solver-0.3.4.dist-info/licenses/LICENSE
chuk_mcp_solver-0.3.4.dist-info/RECORD
