Metadata-Version: 2.4
Name: chuk-mcp-solver
Version: 0.3.4
Summary: General-purpose constraint and optimization solver MCP server
Project-URL: Homepage, https://github.com/chuk-ai/chuk-mcp-solver
Project-URL: Documentation, https://github.com/chuk-ai/chuk-mcp-solver#readme
Project-URL: Repository, https://github.com/chuk-ai/chuk-mcp-solver
Project-URL: Issues, https://github.com/chuk-ai/chuk-mcp-solver/issues
Author-email: CHUK AI <chrishayuk@somejunkmailbox.com>
License: MIT
License-File: LICENSE
Keywords: constraint-solver,cp-sat,mcp,model-context-protocol,optimization,or-tools
Classifier: Development Status :: 3 - Alpha
Classifier: Intended Audience :: Developers
Classifier: License :: OSI Approved :: MIT License
Classifier: Programming Language :: Python :: 3
Classifier: Programming Language :: Python :: 3.11
Classifier: Programming Language :: Python :: 3.12
Classifier: Programming Language :: Python :: 3.13
Requires-Python: >=3.11
Requires-Dist: chuk-mcp-server>=0.8
Requires-Dist: httpx>=0.27.0
Requires-Dist: ortools>=9.10.0
Requires-Dist: pydantic>=2.0.0
Requires-Dist: pyyaml>=6.0.0
Provides-Extra: dev
Requires-Dist: mypy>=1.8.0; extra == 'dev'
Requires-Dist: pytest-asyncio>=0.23.0; extra == 'dev'
Requires-Dist: pytest-cov>=4.1.0; extra == 'dev'
Requires-Dist: pytest>=8.0.0; extra == 'dev'
Requires-Dist: ruff>=0.2.0; extra == 'dev'
Requires-Dist: types-pyyaml>=6.0.0; extra == 'dev'
